pycorelib/__init__.py
pycorelib/async_utils.py
pycorelib/config_loader.py
pycorelib/csv_utils.py
pycorelib/dict_ops.py
pycorelib/fs_utils.py
pycorelib/jsonx.py
pycorelib/num_utils.py
pycorelib/string_tools.py
pycorelib/timer.py
pycorelib-0.1.0.dist-info/METADATA
pycorelib-0.1.0.dist-info/WHEEL
pycorelib-0.1.0.dist-info/top_level.txt
pycorelib-0.1.0.dist-info/RECORD
