Metadata-Version: 2.1
Name: pycorelib
Version: 0.1.0
Summary: A lightweight Python utility library with CSV, JSON, config, async, string, dict, and numeric helpers.
Home-page: https://github.com/sumit333/pycorelib
Author: Sumit Kumar Sharma
Author-email: Sumit Kumar Sharma <sharmasumitk877@gmail.com>
Project-URL: Homepage, https://github.com/sumit333/pycorelib
Project-URL: Issues, https://github.com/sumit333/pycorelib/issues
Keywords: utilities,helpers,csv,json,config,python
Classifier: Programming Language :: Python :: 3
Classifier: License :: OSI Approved :: MIT License
Classifier: Operating System :: OS Independent
Requires-Python: >=3.7
